<system>
	<name>HD 142245</name>
	<rightascension>15 52 56</rightascension>
	<declination>+15 25 51</declination>
	<star>
		<name>HD 142245</name>
		<magV errorminus="0.012" errorplus="0.012">7.452</magV>
		<magJ errorminus="0.018" errorplus="0.018">5.689</magJ>
		<magH errorminus="0.016" errorplus="0.016">5.232</magH>
		<magK errorminus="0.031" errorplus="0.031">5.110</magK>
		<planet>
			<name>HD 142245 b</name>
			<semimajoraxis errorminus="-0.090000" errorplus="0.090000">2.770000</semimajoraxis>
			<eccentricity>0.090000</eccentricity>
			<periastron errorminus="-60.0000" errorplus="60.0000">242.0000</periastron>
			<period errorminus="-48.00000000" errorplus="48.00000000">1299.00000000</period>
			<mass errorminus="-0.20000" errorplus="0.20000">1.90000</mass>
			<discoverymethod>Radial Velocity</discoverymethod>
			<discoveryyear>2011</discoveryyear>
			<lastupdate>2013 03 04</lastupdate>
		</planet>
	</star>
</system>
