<system>
	<name>Kepler-43</name>
	<rightascension>19 00 58</rightascension>
	<declination>+46 40 06</declination>
	<star>
		<name>Kepler-43</name>
		<radius errorminus="0.07" errorplus="0.07">1.42</radius>
		<magJ errorminus="0.022" errorplus="0.022">12.858</magJ>
		<magH errorminus="0.020" errorplus="0.020">12.605</magH>
		<magK errorminus="0.030" errorplus="0.030">12.549</magK>
		<mass errorminus="0.09" errorplus="0.09">1.32</mass>
		<temperature errorminus="143.00" errorplus="143.00">6041.00</temperature>
		<metallicity>[Fe/H]</metallicity>
		<planet>
			<name>Kepler-43 b</name>
			<semimajoraxis errorminus="-0.001000" errorplus="0.001000">0.044900</semimajoraxis>
			<eccentricity>0.025000</eccentricity>
			<inclination errorminus="-0.400" errorplus="0.470">84.350</inclination>
			<period errorminus="-0.00002100" errorplus="0.00002100">3.02409500</period>
			<mass errorminus="-0.19000" errorplus="0.19000">3.23000</mass>
			<radius errorminus="-0.060" errorplus="0.060">1.200</radius>
			<temperature errorminus="-47" errorplus="47">1637</temperature>
			<discoverymethod>Transit</discoverymethod>
			<discoveryyear>2011</discoveryyear>
			<lastupdate>2012 12 11</lastupdate>
			<transittime errorminus="-0.000600" errorplus="0.000600">2454965.415900</transittime>
		</planet>
	</star>
</system>
