<system>
	<name>Kepler-149</name>
	<rightascension>19 03 25</rightascension>
	<declination>+38 23 03</declination>
	<star>
		<name>Kepler-149</name>
		<radius errorminus="0.14" errorplus="0.14">0.95</radius>
		<magJ errorminus="0.023" errorplus="0.023">12.694</magJ>
		<magH errorminus="0.025" errorplus="0.025">12.274</magH>
		<magK errorminus="0.025" errorplus="0.025">12.184</magK>
		<temperature errorminus="100.00" errorplus="100.00">5381.00</temperature>
		<metallicity>[Fe/H]</metallicity>
		<planet>
			<name>Kepler-149 b</name>
			<semimajoraxis>0.184000</semimajoraxis>
			<period errorminus="-0.00004100" errorplus="0.00004100">29.19894300</period>
			<radius errorminus="-0.054" errorplus="0.054">0.376</radius>
			<discoverymethod>Transit</discoverymethod>
			<discoveryyear>2014</discoveryyear>
			<lastupdate>2014 02 26</lastupdate>
			<transittime errorminus="-0.000760" errorplus="0.000760">2455018.440220</transittime>
		</planet>
		<planet>
			<name>Kepler-149 c</name>
			<semimajoraxis>0.281000</semimajoraxis>
			<period errorminus="-0.00194600" errorplus="0.00194600">55.32832800</period>
			<radius errorminus="-0.021" errorplus="0.021">0.144</radius>
			<discoverymethod>Transit</discoverymethod>
			<discoveryyear>2014</discoveryyear>
			<lastupdate>2014 02 26</lastupdate>
			<transittime errorminus="-0.017520" errorplus="0.017520">2455019.326650</transittime>
		</planet>
		<planet>
			<name>Kepler-149 d</name>
			<semimajoraxis>0.571000</semimajoraxis>
			<period errorminus="-0.00109600" errorplus="0.00109600">160.01803200</period>
			<radius errorminus="-0.061" errorplus="0.061">0.353</radius>
			<discoverymethod>Transit</discoverymethod>
			<discoveryyear>2014</discoveryyear>
			<lastupdate>2014 02 26</lastupdate>
			<transittime errorminus="-0.003240" errorplus="0.003240">2455084.283480</transittime>
		</planet>
	</star>
</system>
