<system>
	<name>Kepler-302</name>
	<rightascension>19 37 16</rightascension>
	<declination>+43 37 46</declination>
	<star>
		<name>Kepler-302</name>
		<radius errorminus="0.25" errorplus="0.25">1.22</radius>
		<magJ errorminus="0.026" errorplus="0.026">14.259</magJ>
		<magH errorminus="0.035" errorplus="0.035">13.913</magH>
		<magK errorminus="0.055" errorplus="0.055">13.900</magK>
		<temperature errorminus="107.00" errorplus="107.00">5740.00</temperature>
		<metallicity>[Fe/H]</metallicity>
		<planet>
			<name>Kepler-302 b</name>
			<semimajoraxis>0.193000</semimajoraxis>
			<period errorminus="-0.00020300" errorplus="0.00020300">30.18410400</period>
			<radius errorminus="-0.076" errorplus="0.076">0.362</radius>
			<discoverymethod>Transit</discoverymethod>
			<discoveryyear>2014</discoveryyear>
			<lastupdate>2014 02 26</lastupdate>
			<transittime errorminus="-0.003730" errorplus="0.003730">2454979.640060</transittime>
		</planet>
		<planet>
			<name>Kepler-302 c</name>
			<semimajoraxis>0.503000</semimajoraxis>
			<period errorminus="-0.00042700" errorplus="0.00042700">127.28218400</period>
			<radius errorminus="-0.227" errorplus="0.227">1.111</radius>
			<discoverymethod>Transit</discoverymethod>
			<discoveryyear>2014</discoveryyear>
			<lastupdate>2014 02 26</lastupdate>
			<transittime errorminus="-0.002130" errorplus="0.002130">2454996.889370</transittime>
		</planet>
	</star>
</system>
