<system>
	<name>Kepler-306</name>
	<rightascension>19 14 09</rightascension>
	<declination>+40 36 58</declination>
	<star>
		<name>Kepler-306</name>
		<radius errorminus="0.04" errorplus="0.04">0.72</radius>
		<magJ errorminus="0.027" errorplus="0.027">14.084</magJ>
		<magH errorminus="0.032" errorplus="0.032">13.607</magH>
		<magK errorminus="0.039" errorplus="0.039">13.503</magK>
		<mass>0.82</mass>
		<temperature errorminus="100.00" errorplus="100.00">4954.00</temperature>
		<metallicity>[Fe/H]</metallicity>
		<planet>
			<name>Kepler-306 b</name>
			<semimajoraxis>0.050000</semimajoraxis>
			<period errorminus="-0.00002500" errorplus="0.00002500">4.64618600</period>
			<radius errorminus="-0.009" errorplus="0.009">0.136</radius>
			<discoverymethod>Transit</discoverymethod>
			<discoveryyear>2014</discoveryyear>
			<lastupdate>2014 02 26</lastupdate>
			<transittime errorminus="-0.002570" errorplus="0.002570">2455187.590580</transittime>
		</planet>
		<planet>
			<name>Kepler-306 c</name>
			<semimajoraxis>0.067000</semimajoraxis>
			<period errorminus="-0.00003200" errorplus="0.00003200">7.24019300</period>
			<radius errorminus="-0.017" errorplus="0.017">0.210</radius>
			<discoverymethod>Transit</discoverymethod>
			<discoveryyear>2014</discoveryyear>
			<lastupdate>2014 02 26</lastupdate>
			<transittime errorminus="-0.002190" errorplus="0.002190">2455188.013280</transittime>
		</planet>
		<planet>
			<name>Kepler-306 d</name>
			<semimajoraxis>0.120000</semimajoraxis>
			<period errorminus="-0.00013700" errorplus="0.00013700">17.32664400</period>
			<radius errorminus="-0.021" errorplus="0.021">0.220</radius>
			<discoverymethod>Transit</discoverymethod>
			<discoveryyear>2014</discoveryyear>
			<lastupdate>2014 02 26</lastupdate>
			<transittime errorminus="-0.003960" errorplus="0.003960">2455193.508850</transittime>
		</planet>
		<planet>
			<name>Kepler-306 e</name>
			<semimajoraxis>0.227000</semimajoraxis>
			<period errorminus="-0.00043900" errorplus="0.00043900">44.84097500</period>
			<radius errorminus="-0.013" errorplus="0.013">0.203</radius>
			<discoverymethod>Transit</discoverymethod>
			<discoveryyear>2014</discoveryyear>
			<lastupdate>2014 02 26</lastupdate>
			<transittime errorminus="-0.004460" errorplus="0.004460">2455192.873870</transittime>
		</planet>
	</star>
</system>
