<system>
	<name>Kepler-272</name>
	<rightascension>19 56 31</rightascension>
	<declination>+47 35 38</declination>
	<star>
		<name>Kepler-272</name>
		<radius errorminus="0.50" errorplus="0.50">0.93</radius>
		<magJ errorminus="0.027" errorplus="0.027">13.159</magJ>
		<magH errorminus="0.031" errorplus="0.031">12.833</magH>
		<magK errorminus="0.025" errorplus="0.025">12.708</magK>
		<mass>0.79</mass>
		<temperature errorminus="200.00" errorplus="200.00">5297.00</temperature>
		<metallicity>[Fe/H]</metallicity>
		<planet>
			<name>Kepler-272 b</name>
			<semimajoraxis>0.038000</semimajoraxis>
			<period errorminus="-0.00001700" errorplus="0.00001700">2.97135300</period>
			<radius errorminus="-0.069" errorplus="0.069">0.128</radius>
			<discoverymethod>Transit</discoverymethod>
			<discoveryyear>2014</discoveryyear>
			<lastupdate>2014 02 26</lastupdate>
			<transittime errorminus="-0.003050" errorplus="0.003050">2454967.386750</transittime>
		</planet>
		<planet>
			<name>Kepler-272 c</name>
			<semimajoraxis>0.061000</semimajoraxis>
			<period errorminus="-0.00003700" errorplus="0.00003700">6.05734200</period>
			<radius errorminus="-0.086" errorplus="0.086">0.160</radius>
			<discoverymethod>Transit</discoverymethod>
			<discoveryyear>2014</discoveryyear>
			<lastupdate>2014 02 26</lastupdate>
			<transittime errorminus="-0.003090" errorplus="0.003090">2454968.925490</transittime>
		</planet>
		<planet>
			<name>Kepler-272 d</name>
			<semimajoraxis>0.091000</semimajoraxis>
			<period errorminus="-0.00007300" errorplus="0.00007300">10.93730400</period>
			<radius errorminus="-0.109" errorplus="0.109">0.201</radius>
			<discoverymethod>Transit</discoverymethod>
			<discoveryyear>2014</discoveryyear>
			<lastupdate>2014 02 26</lastupdate>
			<transittime errorminus="-0.003720" errorplus="0.003720">2454969.985030</transittime>
		</planet>
	</star>
</system>
