<system>
	<name>MOA 2011-BLG-293L</name>
	<rightascension>17 55 39</rightascension>
	<declination>-28 28 37</declination>
	<star>
		<name>MOA 2011-BLG-293L</name>
		<magH errorminus="0.030" errorplus="0.030">19.160</magH>
		<mass errorminus="0.06" errorplus="0.06">0.86</mass>
		<planet>
			<name>MOA 2011-BLG-293L b</name>
			<semimajoraxis errorminus="-0.100000" errorplus="0.100000">1.100000</semimajoraxis>
			<mass errorminus="-0.30000" errorplus="0.30000">4.80000</mass>
			<discoverymethod>Microlensing</discoverymethod>
			<discoveryyear>2012</discoveryyear>
			<lastupdate>2013 10 15</lastupdate>
		</planet>
	</star>
</system>
