<system>
	<name>HD 109246</name>
	<rightascension>12 32 07</rightascension>
	<declination>+74 29 22</declination>
	<distance>65.6</distance>
	<star>
		<name>HD 109246</name>
		<radius>1.02</radius>
		<mass>1.01</mass>
		<spectraltype>GOV</spectraltype>
		<temperature>5844.0</temperature>
		<metallicity>0.1</metallicity>
		<planet>
			<name>HD 109246 b</name>
			<semimajoraxis errorminus="0.08" errorplus="0.08">0.33</semimajoraxis>
			<periastron errorminus="29.0" errorplus="29.0">235.0</periastron>
			<eccentricity errorminus="0.04" errorplus="0.04">0.12</eccentricity>
			<period errorminus="0.13" errorplus="0.13">68.27</period>
			<mass errorminus="0.09" errorplus="0.09">0.77</mass>
			<discoverymethod>RV</discoverymethod>
			<discoveryyear>2010</discoveryyear>
			<lastupdate>10/06/28</lastupdate>
		</planet>
	</star>
</system>
