<system>
	<name>Kepler-172</name>
	<rightascension>18 53 28</rightascension>
	<declination>+41 49 19</declination>
	<star>
		<name>Kepler-172</name>
		<radius>1.08</radius>
		<mass>0.86</mass>
		<temperature>5526.0</temperature>
		<metallicity>0.012</metallicity>
		<planet>
			<name>Kepler-172 b</name>
			<semimajoraxis>0.04</semimajoraxis>
			<period errorminus="0.000007" errorplus="0.000007">2.940309</period>
			<radius errorminus="0.037" errorplus="0.037">0.21</radius>
			<istransiting>1</istransiting>
			<discoverymethod>transit</discoverymethod>
			<discoveryyear>2014</discoveryyear>
			<lastupdate>14/03/06</lastupdate>
			<list>Confirmed planets</list>
			<description>Data for this planet was imported from the exoplanet.eu database.</description>
		</planet>
		<planet>
			<name>Kepler-172 c</name>
			<semimajoraxis>0.068</semimajoraxis>
			<period errorminus="0.000020" errorplus="0.000020">6.388996</period>
			<radius errorminus="0.047" errorplus="0.047">0.255</radius>
			<istransiting>1</istransiting>
			<discoverymethod>transit</discoverymethod>
			<discoveryyear>2014</discoveryyear>
			<lastupdate>14/03/06</lastupdate>
			<list>Confirmed planets</list>
			<description>Data for this planet was imported from the exoplanet.eu database.</description>
		</planet>
		<planet>
			<name>Kepler-172 d</name>
			<semimajoraxis>0.118</semimajoraxis>
			<period errorminus="0.000105" errorplus="0.000105">14.627119</period>
			<radius errorminus="0.036" errorplus="0.036">0.201</radius>
			<istransiting>1</istransiting>
			<discoverymethod>transit</discoverymethod>
			<discoveryyear>2014</discoveryyear>
			<lastupdate>14/03/06</lastupdate>
			<list>Confirmed planets</list>
			<description>Data for this planet was imported from the exoplanet.eu database.</description>
		</planet>
		<planet>
			<name>Kepler-172 e</name>
			<semimajoraxis>0.211</semimajoraxis>
			<period errorminus="0.000253" errorplus="0.000253">35.118736</period>
			<radius errorminus="0.05" errorplus="0.05">0.246</radius>
			<istransiting>1</istransiting>
			<discoverymethod>transit</discoverymethod>
			<discoveryyear>2014</discoveryyear>
			<lastupdate>14/03/06</lastupdate>
			<list>Confirmed planets</list>
			<description>Data for this planet was imported from the exoplanet.eu database.</description>
		</planet>
	</star>
</system>
