<system>
	<name>Kepler-362</name>
	<rightascension>19 27 05</rightascension>
	<declination>+47 31 48</declination>
	<star>
		<name>Kepler-362</name>
		<radius>0.72</radius>
		<mass>0.77</mass>
		<temperature>5788.0</temperature>
		<metallicity>-0.718</metallicity>
		<planet>
			<name>Kepler-362 b</name>
			<semimajoraxis>0.087</semimajoraxis>
			<period errorminus="0.000101" errorplus="0.000101">10.327186</period>
			<radius errorminus="0.034" errorplus="0.034">0.079</radius>
			<discoverymethod>transit</discoverymethod>
			<discoveryyear>2014</discoveryyear>
			<lastupdate>14/03/06</lastupdate>
		</planet>
		<planet>
			<name>Kepler-362 c</name>
			<semimajoraxis>0.207</semimajoraxis>
			<period errorminus="0.000298" errorplus="0.000298">37.866281</period>
			<radius errorminus="0.054" errorplus="0.054">0.129</radius>
			<discoverymethod>transit</discoverymethod>
			<discoveryyear>2014</discoveryyear>
			<lastupdate>14/03/06</lastupdate>
		</planet>
	</star>
</system>
