<system>
	<name>Kepler-208</name>
	<rightascension>19 35 34</rightascension>
	<declination>+42 31 41</declination>
	<star>
		<name>Kepler-208</name>
		<radius>1.31</radius>
		<mass>1.03</mass>
		<temperature>6092.0</temperature>
		<planet>
			<name>Kepler-208 b</name>
			<semimajoraxis>0.054</semimajoraxis>
			<period errorminus="0.000018" errorplus="0.000018">4.22864</period>
			<radius errorminus="0.027" errorplus="0.027">0.145</radius>
			<istransiting>1</istransiting>
			<discoverymethod>transit</discoverymethod>
			<discoveryyear>2014</discoveryyear>
			<lastupdate>14/03/06</lastupdate>
			<list>Confirmed planets</list>
			<description>Data for this planet was imported from the exoplanet.eu database.</description>
		</planet>
		<planet>
			<name>Kepler-208 c</name>
			<semimajoraxis>0.079</semimajoraxis>
			<period errorminus="0.000067" errorplus="0.000067">7.466623</period>
			<radius errorminus="0.023" errorplus="0.023">0.124</radius>
			<istransiting>1</istransiting>
			<discoverymethod>transit</discoverymethod>
			<discoveryyear>2014</discoveryyear>
			<lastupdate>14/03/06</lastupdate>
			<list>Confirmed planets</list>
			<description>Data for this planet was imported from the exoplanet.eu database.</description>
		</planet>
		<planet>
			<name>Kepler-208 d</name>
			<semimajoraxis>0.103</semimajoraxis>
			<period errorminus="0.000131" errorplus="0.000131">11.131786</period>
			<radius errorminus="0.021" errorplus="0.021">0.107</radius>
			<istransiting>1</istransiting>
			<discoverymethod>transit</discoverymethod>
			<discoveryyear>2014</discoveryyear>
			<lastupdate>14/03/06</lastupdate>
			<list>Confirmed planets</list>
			<description>Data for this planet was imported from the exoplanet.eu database.</description>
		</planet>
		<planet>
			<name>Kepler-208 e</name>
			<semimajoraxis>0.132</semimajoraxis>
			<period errorminus="0.000176" errorplus="0.000176">16.259458</period>
			<radius errorminus="0.025" errorplus="0.025">0.132</radius>
			<istransiting>1</istransiting>
			<discoverymethod>transit</discoverymethod>
			<discoveryyear>2014</discoveryyear>
			<lastupdate>14/03/06</lastupdate>
			<list>Confirmed planets</list>
			<description>Data for this planet was imported from the exoplanet.eu database.</description>
		</planet>
	</star>
</system>
