<system>
	<name>KOI-1574</name>
	<rightascension>19 51 40</rightascension>
	<declination>+46 57 54</declination>
	<star>
		<name>KOI-1574</name>
		<age>7.5</age>
		<radius>1.82</radius>
		<mass>1.1</mass>
		<temperature>5600.0</temperature>
		<metallicity>-0.17</metallicity>
		<planet>
			<name>Kepler-87 b</name>
			<semimajoraxis errorminus="0.028" errorplus="0.028">0.471</semimajoraxis>
			<periastron errorminus="27.6" errorplus="27.6">238.6</periastron>
			<eccentricity errorminus="0.009" errorplus="0.009">0.036</eccentricity>
			<inclination errorminus="0.034" errorplus="0.034">89.274</inclination>
			<period errorminus="0.000260" errorplus="0.000260">114.73709</period>
			<mass errorminus="0.16" errorplus="0.16">1.02</mass>
			<radius errorminus="0.006" errorplus="0.006">1.21</radius>
			<istransiting>1</istransiting>
			<discoverymethod>transit</discoverymethod>
			<discoveryyear>2013</discoveryyear>
			<lastupdate>13/10/11</lastupdate>
			<list>Confirmed planets</list>
			<description>Data for this planet was imported from the exoplanet.eu database.</description>
		</planet>
		<planet>
			<name>Kepler-87 c</name>
			<semimajoraxis errorminus="0.013" errorplus="0.013">0.664</semimajoraxis>
			<periastron errorminus="18.8" errorplus="18.8">223.2</periastron>
			<eccentricity errorminus="0.012" errorplus="0.012">0.039</eccentricity>
			<inclination errorminus="0.031" errorplus="0.031">89.588</inclination>
			<period errorminus="0.007400" errorplus="0.007400">192.363</period>
			<mass errorminus="0.01" errorplus="0.01">0.0201</mass>
			<radius errorminus="0.008" errorplus="0.008">0.549</radius>
			<istransiting>1</istransiting>
			<discoverymethod>transit</discoverymethod>
			<discoveryyear>2012</discoveryyear>
			<lastupdate>13/10/11</lastupdate>
			<list>Confirmed planets</list>
			<description>Data for this planet was imported from the exoplanet.eu database.</description>
		</planet>
	</star>
</system>
